converter/__init__.py
converter/converter.py
xlsxCsvConverterrr-1.0.2.dist-info/LICENSE
xlsxCsvConverterrr-1.0.2.dist-info/METADATA
xlsxCsvConverterrr-1.0.2.dist-info/WHEEL
xlsxCsvConverterrr-1.0.2.dist-info/top_level.txt
xlsxCsvConverterrr-1.0.2.dist-info/RECORD
