Metadata-Version: 2.1
Name: xlsxCsvConverterrr
Version: 1.0.2
Summary: Сonverting xlsx to csv and vice versa.
Home-page: https://github.com/Vafernti/MPEI-Project
Author: Fernatii I.K.
Author-email: fernatii_ivan@mail.ru
License: UNKNOWN
Platform: any
Requires-Python: >=3.7
Requires-Dist: et-xmlfile (>=1.1.0)
Requires-Dist: numpy (>=1.21.0)
Requires-Dist: openpyxl (>=3.0.7)
Requires-Dist: pandas (>=1.2.5)
Requires-Dist: python-dateutil (>=2.8.1)
Requires-Dist: pytz (>=2021.1)
Requires-Dist: six (>=1.16.0)
